<?xml version="1.0" encoding="UTF-8"?><record_update>
    <sys_choice action="DELETE" field="u_request_type" table="x_58872_needit_needit" version="3">
        <sys_choice_set action="DELETE">
            <element>u_request_type</element>
            <name>x_58872_needit_needit</name>
            <sys_class_name/>
            <sys_created_by/>
            <sys_created_on/>
            <sys_id/>
            <sys_mod_count/>
            <sys_name/>
            <sys_package/>
            <sys_policy/>
            <sys_scope/>
            <sys_update_name/>
            <sys_updated_by/>
            <sys_updated_on>2019-12-10 15:44:07</sys_updated_on>
        </sys_choice_set>
    </sys_choice>
    <sys_update_version action="INSERT_OR_UPDATE">
        <action>DELETE</action>
        <application/>
        <file_path/>
        <instance_id>3b56c7d8db51f7802f68c5970596197c</instance_id>
        <instance_name>dev85081</instance_name>
        <name>sys_choice_x_58872_needit_needit_u_request_type</name>
        <payload><![CDATA[<?xml version="1.0" encoding="UTF-8"?><record_update><sys_choice action="DELETE" field="u_request_type" table="x_58872_needit_needit" version="3"><sys_choice_set action="DELETE"><element>u_request_type</element><name>x_58872_needit_needit</name><sys_class_name/><sys_created_by/><sys_created_on/><sys_id/><sys_mod_count/><sys_name/><sys_package/><sys_policy/><sys_scope/><sys_update_name/><sys_updated_by/><sys_updated_on>2019-12-10 15:44:07</sys_updated_on></sys_choice_set></sys_choice></record_update>]]></payload>
        <payload_hash>1828161538</payload_hash>
        <record_name>x_58872_needit_needit.u_request_type</record_name>
        <reverted_from/>
        <source>ea76fbf6db2100101d3b6f774896195b</source>
        <source_table>sys_update_set</source_table>
        <state>previous</state>
        <sys_created_by>admin</sys_created_by>
        <sys_created_on>2019-12-10 15:44:07</sys_created_on>
        <sys_id>67e6214fdba500101d3b6f7748961964</sys_id>
        <sys_mod_count>0</sys_mod_count>
        <sys_recorded_at>16ef07b5f420000001</sys_recorded_at>
        <sys_updated_by>admin</sys_updated_by>
        <sys_updated_on>2019-12-10 15:44:07</sys_updated_on>
        <type>Choice list</type>
        <update_guid>efe6214fdea5001094b1bb7c37c73963</update_guid>
        <update_guid_history>efe6214fdea5001094b1bb7c37c73963:1828161538,abe6214f6fa5001042ccdc1a412a2360:2107296794,2be6214f7da50010fb73bb1fd47f405d:1356028415,a7e6214fafa500100666fe6d4b0ffe5a:-1205683529,6f118dcb3a2500101ab6740494added1:-1673223470</update_guid_history>
    </sys_update_version>
    <sys_metadata_delete action="INSERT_OR_UPDATE">
        <sys_audit_delete/>
        <sys_class_name>sys_metadata_delete</sys_class_name>
        <sys_created_by>admin</sys_created_by>
        <sys_created_on>2019-12-10 15:44:16</sys_created_on>
        <sys_db_object display_value="" name="sys_choice_set">sys_choice_set</sys_db_object>
        <sys_id>5df6a14fdba500101d3b6f774896195f</sys_id>
        <sys_metadata>5df6a14fdba500101d3b6f774896195f</sys_metadata>
        <sys_mod_count>0</sys_mod_count>
        <sys_name>u_request_type</sys_name>
        <sys_package display_value="NeedIt" source="x_58872_needit">6ead8e780f603200cd674f8ce1050ed1</sys_package>
        <sys_parent/>
        <sys_policy/>
        <sys_scope display_value="NeedIt">6ead8e780f603200cd674f8ce1050ed1</sys_scope>
        <sys_scope_delete display_value="">94872a8897db403e8ee69a431de2fca4</sys_scope_delete>
        <sys_update_name>sys_choice_x_58872_needit_needit_u_request_type</sys_update_name>
        <sys_update_version display_value="sys_choice_x_58872_needit_needit_u_request_type">67e6214fdba500101d3b6f7748961964</sys_update_version>
        <sys_updated_by>admin</sys_updated_by>
        <sys_updated_on>2019-12-10 15:44:16</sys_updated_on>
    </sys_metadata_delete>
</record_update>
